pyleaps.py
pyleaps-0.0.2.dist-info/LICENSE
pyleaps-0.0.2.dist-info/METADATA
pyleaps-0.0.2.dist-info/WHEEL
pyleaps-0.0.2.dist-info/top_level.txt
pyleaps-0.0.2.dist-info/RECORD
