Metadata-Version: 2.1
Name: pyleaps
Version: 0.0.2
Summary: Simple porting of the LEAPS package on python. Not optimized yet.
Author: Fortunato Nucera
License: UNKNOWN
Platform: UNKNOWN
Classifier: Programming Language :: Python :: 3
Classifier: License :: OSI Approved :: MIT License
Classifier: Operating System :: OS Independent
Requires-Python: >=3.6
License-File: LICENSE
Requires-Dist: numpy
Requires-Dist: statsmodels
Requires-Dist: pandas
